rsbio_seq-0.1.5.dist-info/METADATA
rsbio_seq-0.1.5.dist-info/WHEEL
rsbio_seq-0.1.5.dist-info/licenses/LICENSE
rsbio_seq/__init__.py
rsbio_seq/__init__.pyi
rsbio_seq/py.typed
rsbio_seq/rsbio_seq.abi3.so
rsbio_seq-0.1.5.dist-info/RECORD
