Metadata-Version: 2.4
Name: rsbio-seq
Version: 0.1.5
Classifier: Programming Language :: Rust
Classifier: Programming Language :: Python :: Implementation :: CPython
Classifier: Programming Language :: Python :: Implementation :: PyPy
License-File: LICENSE
License-File: LICENSE
Summary: RSBio-Seq is a fast and light-weight sequence reading library (built on top of rust bio crate).
Keywords: bioinformatics,genomics
Author: Anuradha Wickramarachchi <anuradhawick@gmail.com>, Vijini Mallawaarachchi <viji.mallawaarachchi@gmail.com>
Author-email: Anuradha Wickramarachchi <anuradhawick@gmail.com>, Vijini Mallawaarachchi <viji.mallawaarachchi@gmail.com>
Requires-Python: >=3.9
Project-URL: Documentation, https://github.com/anuradhawick/rsbio-seq/
Project-URL: Bug Tracker, https://github.com/anuradhawick/rsbio-seq/issues
Project-URL: Source Code, https://github.com/anuradhawick/rsbio-seq/
